NPHIconvert.py
NPHIconvert-0.0.2.dist-info/LICENSE.txt
NPHIconvert-0.0.2.dist-info/METADATA
NPHIconvert-0.0.2.dist-info/WHEEL
NPHIconvert-0.0.2.dist-info/top_level.txt
NPHIconvert-0.0.2.dist-info/RECORD
