Metadata-Version: 2.1
Name: NPHIconvert
Version: 0.0.2
Summary: Apparent Neutron Porosity to True Porosity Conversion
Home-page: https://github.com/farooqad0/NPHIconvert
Author: Farooq Arshad
Author-email: farooqad0@gmail.com
License: UNKNOWN
Platform: UNKNOWN
Classifier: Intended Audience :: Education
Classifier: Operating System :: Microsoft :: Windows :: Windows 10
Classifier: License :: OSI Approved :: GNU Affero General Public License v3 or later (AGPLv3+)
Classifier: Programming Language :: Python :: 3
Requires-Dist: numpy (>=1.15)
Requires-Dist: matplotlib (>=3.0)
